samlibs_generate_password/__init__.py
samlibs_generate_password/generator.py
samlibs_generate_password-1.0.0.dist-info/licenses/LICENSE
samlibs_generate_password-1.0.0.dist-info/METADATA
samlibs_generate_password-1.0.0.dist-info/WHEEL
samlibs_generate_password-1.0.0.dist-info/top_level.txt
samlibs_generate_password-1.0.0.dist-info/RECORD
