Metadata-Version: 2.4
Name: samlibs-generate-password
Version: 1.0.0
Summary: A lightweight, fast, and optimized password generator library for Python
Home-page: https://github.com/themrsami/samlibs-generate-password-python
Author: themrsami
Author-email: usamanazir13@gmail.com
Project-URL: Bug Reports, https://github.com/themrsami/samlibs-generate-password-python/issues
Project-URL: Source, https://github.com/themrsami/samlibs-generate-password-python
Project-URL: Documentation, https://github.com/themrsami/samlibs-generate-password-python#readme
Keywords: password,generator,random,security,lightweight,fast,samlibs,cryptography
Classifier: Development Status :: 5 - Production/Stable
Classifier: Intended Audience :: Developers
Classifier: License :: OSI Approved :: MIT License
Classifier: Operating System :: OS Independent
Classifier: Programming Language :: Python :: 3
Classifier: Programming Language :: Python :: 3.6
Classifier: Programming Language :: Python :: 3.7
Classifier: Programming Language :: Python :: 3.8
Classifier: Programming Language :: Python :: 3.9
Classifier: Programming Language :: Python :: 3.10
Classifier: Programming Language :: Python :: 3.11
Classifier: Programming Language :: Python :: 3.12
Classifier: Topic :: Security
Classifier: Topic :: Security :: Cryptography
Classifier: Topic :: Software Development :: Libraries :: Python Modules
Classifier: Topic :: Utilities
Requires-Python: >=3.6
License-File: LICENSE
Dynamic: author
Dynamic: author-email
Dynamic: classifier
Dynamic: description
Dynamic: description-content-type
Dynamic: home-page
Dynamic: keywords
Dynamic: license-file
Dynamic: project-url
Dynamic: requires-python
Dynamic: summary
